pdm_unasync-0.1.1.dist-info/METADATA
pdm_unasync-0.1.1.dist-info/WHEEL
pdm_unasync-0.1.1.dist-info/entry_points.txt
pdm_unasync/__init__.py
pdm_unasync/py.typed
pdm_unasync-0.1.1.dist-info/RECORD
