Metadata-Version: 2.1
Name: pdm-unasync
Version: 0.1.1
Summary: Default template for PDM package
Author-Email: "Kalle M. Aagaard" <git@k-moeller.dk>
License: MIT
Requires-Python: >=3.12
Requires-Dist: pdm>=2.15.4
Requires-Dist: unasync>=0.6.0
